conf.py
pyrop/__init__.py
pyrop/_catch.py
pyrop/_either.py
pyrop/_option.py
version.py
pyrop-1.0.0.dist-info/WHEEL
pyrop-1.0.0.dist-info/LICENSE.md
pyrop-1.0.0.dist-info/METADATA
pyrop-1.0.0.dist-info/RECORD
