Metadata-Version: 2.1
Name: pyrop
Version: 1.0.0
Summary: Imperative-style railway-oriented programming in Python
License: MIT
Author: Nick DeRobertis
Author-email: derobertis.nick@gmail.com
Requires-Python: >=3.9
Classifier: Development Status :: 3 - Alpha
Classifier: Intended Audience :: Developers
Classifier: License :: OSI Approved :: MIT License
Classifier: Programming Language :: Python :: 3
Classifier: Programming Language :: Python :: 3.9
Classifier: Programming Language :: Python :: 3.10
Classifier: Programming Language :: Python :: 3.11
Classifier: Programming Language :: Python :: 3.10
Classifier: Programming Language :: Python :: 3.11
Classifier: Programming Language :: Python :: 3.7
Classifier: Programming Language :: Python :: 3.8
Classifier: Programming Language :: Python :: 3.9
Requires-Dist: typing-extensions (>=3.10.0.0)
Project-URL: documentation, https://nickderobertis.github.io/pyrop
Project-URL: repository, https://github.com/nickderobertis/pyrop
